my_pwm.py
my_pwm-0.0.9.1.dist-info/entry_points.txt
my_pwm-0.0.9.1.dist-info/LICENSE
my_pwm-0.0.9.1.dist-info/WHEEL
my_pwm-0.0.9.1.dist-info/METADATA
my_pwm-0.0.9.1.dist-info/RECORD
